{
  "id": "check_sitecat_plugins1",
  "icon_url": "https://tealium-tools.s3.amazonaws.com/tools/logo.png",
  "title": "Check SiteCatalyst Plugins",
  "description": "This tool checks for the existence of various SiteCatalyst plugins.",
  "scripts": {
    "check_plugins": {
      "title": "SiteCatalyst plugins",
      "description": "Check the version of the plugins installed in SiteCatalyst.",
      "button_label": "Scan plugins",
      "template": "http://localhost:8080/check_plugins-template.html?123",
      "js": "http://localhost:8080/check_plugins-script.js?123",
      "remote_js": true,
      "remote_template": true
    }
  }
}